niwatoko/__init__.py
niwatoko/cli.py
niwatoko/metadata.json
niwatoko/temp.py
niwatoko/foundation_model/interpretation/llm/claude.py
niwatoko/foundation_model/interpretation/llm/gpt.py
niwatoko/grammar/system.md
tests/README.md
tests/__init__.py
tests/test_compiler.md
tests/test_compiler.py
tests/test_compiler_v1_2.py
tests/test_interpreter.py
tests/test_parser.py
tests/test_docs/__init__.py
tests/test_docs/output copy.md
tests/test_docs/output.md
tests/test_docs/output.py
tests/test_docs/output_.md
tests/test_docs/test_doc1.md
tests/test_docs/test_doc2.md
tests/test_docs/test_doc3.md
tests/test_docs/test_gen_github_issue.md
tests/test_docs/test_gen_grimoire.md
tests/test_docs/test_gen_grimoire2.md
tests/test_docs/test_gen_grimoire_en.md
tests/test_docs/test_gen_zoltraak_pypi.md
tests/test_docs/test_import_function.md
tests/test_docs/test_import_md.md
tests/test_docs/test_import_module_add.py
tests/test_docs/test_import_module_multiple.py
tests/test_docs/test_input.md
niwatoko-1.2.41.dist-info/LICENSE
niwatoko-1.2.41.dist-info/METADATA
niwatoko-1.2.41.dist-info/WHEEL
niwatoko-1.2.41.dist-info/entry_points.txt
niwatoko-1.2.41.dist-info/top_level.txt
niwatoko-1.2.41.dist-info/RECORD
