Metadata-Version: 2.1
Name: niwatoko
Version: 1.2.41
Summary: 自然言語でプログラミングを行うことができる新しいプログラミング言語
Home-page: https://niwatoko2.vercel.app/
Author: dai-motoki
Author-email: dai.motoki1123@gmail.com
Classifier: Development Status :: 5 - Production/Stable
Classifier: Intended Audience :: Developers
Classifier: Natural Language :: Japanese
Classifier: Programming Language :: Python :: 3
Classifier: Programming Language :: Python :: 3.7
Classifier: Programming Language :: Python :: 3.8
Classifier: Programming Language :: Python :: 3.9
Classifier: Programming Language :: Python :: 3.10
Classifier: Programming Language :: Python :: 3.11
Classifier: License :: OSI Approved :: MIT License
Classifier: Operating System :: OS Independent
Requires-Python: >=3.7
License-File: LICENSE
Requires-Dist: streamlit
Requires-Dist: openai
Requires-Dist: anthropic
Requires-Dist: opencv-python
Requires-Dist: moviepy
Requires-Dist: google-cloud-aiplatform
Requires-Dist: python-dotenv
